README.md
setup.py
iberzetsn/__init__.py
iberzetsn/from_yiddish.py
iberzetsn/letters.py
iberzetsn/to_yiddish.py
iberzetsn.egg-info/PKG-INFO
iberzetsn.egg-info/SOURCES.txt
iberzetsn.egg-info/dependency_links.txt
iberzetsn.egg-info/top_level.txt