Metadata-Version: 1.0
Name: iberzetsn
Version: 0.1.1
Summary: A library for Yiddish transliteration
Home-page: https://github.com/jwg4/iberzetsn
Author: Jack Grahl
Author-email: jack.grahl@gmail.com
License: MIT
Platform: UNKNOWN
